getweatherunderground/__init__.py
getweatherunderground/client.py
get_weather_api-0.1.5.dist-info/METADATA
get_weather_api-0.1.5.dist-info/WHEEL
get_weather_api-0.1.5.dist-info/top_level.txt
get_weather_api-0.1.5.dist-info/RECORD
