Metadata-Version: 2.4
Name: get_weather_api
Version: 0.1.5
Summary: A simple API key example package
Author-email: JP Talusan <jptalusan@gmail.com>
Project-URL: Homepage, https://github.com/jptalusan/get_weather
Requires-Python: >=3.7
Requires-Dist: python-dotenv
Requires-Dist: pandas>=2.1.0
Requires-Dist: pytz
Requires-Dist: requests~=2.31.0
Provides-Extra: dev
Requires-Dist: pytest; extra == "dev"
